simple_localization/__init__.py
simple_localization/localization.py
simple_localization-1.0.2.dist-info/LICENSE
simple_localization-1.0.2.dist-info/METADATA
simple_localization-1.0.2.dist-info/WHEEL
simple_localization-1.0.2.dist-info/top_level.txt
simple_localization-1.0.2.dist-info/RECORD
