Metadata-Version: 2.1
Name: simple-localization
Version: 1.0.2
Summary: A simple localization package
Home-page: https://github.com/MyselfLeo/simple-localization
Author: myselfleo
Author-email: myselfleo@outlook.fr
License: UNKNOWN
Project-URL: Bug Tracker, https://github.com/MyselfLeo/simple-localization/issues
Platform: UNKNOWN
Classifier: Programming Language :: Python :: 3
Classifier: License :: OSI Approved :: GNU General Public License v3 (GPLv3)
Classifier: Operating System :: OS Independent
Requires-Python: >=3.6
License-File: LICENSE
